{
	"name": "DS_input",
	"properties": {
		"linkedServiceName": {
			"referenceName": "LS_AzureBlobStorage",
			"type": "LinkedServiceReference"
		},
		"annotations": [],
		"type": "DelimitedText",
		"typeProperties": {
			"location": {
				"type": "AzureBlobStorageLocation",
				"fileName": "data.csv",
				"container": "input"
			},
			"columnDelimiter": ",",
			"escapeChar": "\\",
			"firstRowAsHeader": true,
			"quoteChar": "\""
		},
		"schema": [
			{
				"name": "f1",
				"type": "String"
			},
			{
				"name": "f2",
				"type": "String"
			}
		]
	},
	"type": "Microsoft.DataFactory/factories/datasets"
}